febs
